{
  "type": "minecraft:huge_fungus",
  "config": {
    "decor_state": {
      "Name": "cyra:sea_stone"
    },
    "hat_state": {
      "Name": "cyra:sea_stone"
    },
    "planted": false,
    "replaceable_blocks": {
      "type": "minecraft:matching_blocks",
      "blocks": "cyra:sea_stone"
    },
    "stem_state": {
      "Name": "cyra:prismatic_leaves",
      "Properties": {
        "distance": "7",
        "persistent": "false",
        "waterlogged": "false"
      }
    },
    "valid_base_block": {
      "Name": "minecraft:amethyst_block"
    }
  }
}